README.md
setup.py
PyBuilder/__init__.py
PyBuilder/_hook.py
PyBuilder/build.py
PyBuilder/compile.py
PyBuilder/config.py
PyBuilder/data.py
PyBuilder/main.py
PyBuilder/run.py
PyBuilder/utils.py
PyBuilder_exe.egg-info/PKG-INFO
PyBuilder_exe.egg-info/SOURCES.txt
PyBuilder_exe.egg-info/dependency_links.txt
PyBuilder_exe.egg-info/entry_points.txt
PyBuilder_exe.egg-info/requires.txt
PyBuilder_exe.egg-info/top_level.txt
PyBuilder_exe.egg-info/zip-safe